dc_auth/__init__.py
dc_auth/_version.py
dc_auth/apps.py
dc_auth/backends.py
dc_auth/models.py
dc_auth/settings.py
dc_auth/settings_testing.py
dc_auth/signals.py
dc_auth/urls.py
dc_auth/drf_support/__init__.py
dc_auth/migrations/0001_initial.py
dc_auth/migrations/0002_remove_profile_email_confirmed.py
dc_auth/migrations/0003_profile_email_confirmed.py
dc_auth/migrations/0004_profileemail.py
dc_auth/migrations/__init__.py
dc_auth/templates/cookielaw/banner.html
dc_auth/templates/dc_auth/base.html
dc_auth/templates/dc_auth/footer.html
dc_auth/templates/dc_auth/messages.html
dc_auth/templates/dc_auth/primary_navbar.html
dc_auth/templates/dc_auth/email/base-64-logo.html
dc_auth/templates/dc_auth/email/base.html
dc_auth/templates/dc_auth/email/test_email.html
dc_auth/templates/dc_auth/form/render.html
dc_auth/templates/dc_auth/header/analytics.html
dc_auth/templates/dc_auth/header/meta.html
dc_auth/templates/dc_auth/header/style.html
dc_auth/templates/dc_auth/header/title.html
dc_auth/templatetags/__init__.py
dc_auth/templatetags/dc_form_helpers.py
dc_auth/templatetags/dc_static.py
dc_auth/testing_support/__init__.py
dc_auth/testing_support/factories/__init__.py
dc_auth/testing_support/factories/user.py
dc_auth-1.4.0.dist-info/licenses/LICENSE
dc_auth-1.4.0.dist-info/METADATA
dc_auth-1.4.0.dist-info/WHEEL
dc_auth-1.4.0.dist-info/entry_points.txt
dc_auth-1.4.0.dist-info/top_level.txt
dc_auth-1.4.0.dist-info/RECORD
